{
    "orders": [
        
        {
            "id": 1,
            "type": 1,
            "quantity": 10
        },
        {
            "id": 2,
            "type": 2,
            "quantity": 10
        },
        {
            "id": 3,
            "type": 3,
            "quantity": 10
        },
        {
            "id": 4,
            "type": 3,
            "quantity" : 30
        },
        {
            "id": 5,
            "type": 1,
            "quantity" : 30
        },
        {
            "id": 6,
            "type": 3,
            "quantity" : 30
        },
        {
            "id": 7,
            "type": 1,
            "quantity" : 100
        },
        {
            "id": 8,
            "type": 2,
            "quantity" : 35
        },
        {
            "id": 9,
            "type": 2,
            "quantity": 20
        },
        {
            "id": 10,
            "type": 3,
            "quantity": 20
        },
        {
            "id": 11,
            "type": 2,
            "quantity": 40
        },
        {
            "id": 12,
            "type": 1,
            "quantity": 60
        },
        {
            "id": 13,
            "type": 2,
            "quantity": 30
        },
        {
            "id": 14,
            "type": 2,
            "quantity": 10
        },
        {
            "id": 15,
            "type": 3,
            "quantity": 75
        },

        {
            "id": 16,
            "type": 1,
            "quantity": 20
        },

        {
            "id": 17,
            "type": 2,
            "quantity": 25
        },

        {
            "id": 18,
            "type": 3,
            "quantity": 40
        },

        {
            "id": 19,
            "type": 1,
            "quantity": 50
        },

        {
            "id": 20,
            "type": 2,
            "quantity": 15
        },
        {
            "id": 21,
            "type": 3,
            "quantity": 60
        }
    ]
}